visiontemplate/__init__.py
visiontemplate-0.1.0.dist-info/METADATA
visiontemplate-0.1.0.dist-info/WHEEL
visiontemplate-0.1.0.dist-info/licenses/LICENSE
visiontemplate-0.1.0.dist-info/RECORD
